pybookreader/__init__.py
pybookreader/book_actions.py
pybookreader/settings.py
pybookreader/utils.py
pybookreader/models/__init__.py
pybookreader/models/base.py
pybookreader/models/book.py
PyBookReader-1.0.1.dist-info/METADATA
PyBookReader-1.0.1.dist-info/WHEEL
PyBookReader-1.0.1.dist-info/entry_points.txt
PyBookReader-1.0.1.dist-info/top_level.txt
PyBookReader-1.0.1.dist-info/RECORD
