Metadata-Version: 2.1
Name: PyBookReader
Version: 1.0.1
Summary: UNKNOWN
Home-page: https://github.com/dangquangdon/Python-Book-Reader-CLI
License: UNKNOWN
Platform: UNKNOWN
Requires-Dist: click (==7.1.2)
Requires-Dist: pyttsx3 (==2.90)
Requires-Dist: SQLAlchemy (==1.3.20)
Requires-Dist: tabulate (==0.8.7)
Requires-Dist: pdftotext (==2.1.5)
Requires-Dist: alembic (==1.4.3)
Requires-Dist: keyboard (==0.13.5)
Requires-Dist: black
Requires-Dist: wheel
Requires-Dist: twine
